diskmap/__init__.py
diskmap/_version.py
diskmap/diskmap.py
diskmap-0.3.3.dist-info/licenses/LICENSE
diskmap-0.3.3.dist-info/METADATA
diskmap-0.3.3.dist-info/WHEEL
diskmap-0.3.3.dist-info/top_level.txt
diskmap-0.3.3.dist-info/RECORD
